fild_ui/__init__.py
fild_ui/browser.py
fild_ui/elements.py
fild_ui/folder.py
fild_ui/indexed_db.py
fild_ui/local_storage.py
fild_ui/pytest_addons.py
fild_ui/screenshots.py
fild_ui/singleton.py
fild_ui-0.1.10.dist-info/licenses/LICENSE
fild_ui-0.1.10.dist-info/METADATA
fild_ui-0.1.10.dist-info/WHEEL
fild_ui-0.1.10.dist-info/top_level.txt
fild_ui-0.1.10.dist-info/RECORD
