Metadata-Version: 2.4
Name: fild-ui
Version: 0.1.10
Summary: Operate with Web UI using selenium and fild library
Home-page: https://github.com/elenakulgavaya/fild-ui
Author: Elena Kulgavaya
Author-email: elena.kulgavaya@gmail.com
Project-URL: Bug Tracker, https://github.com/elenakulgavaya/fild-ui/issues
Classifier: Programming Language :: Python :: 3
Classifier: License :: OSI Approved :: MIT License
Classifier: Operating System :: OS Independent
Requires-Python: >=3.9
License-File: LICENSE
Requires-Dist: fild>=0.1.0
Requires-Dist: fild-compare>=0.0.3
Requires-Dist: fild>=0.0.8
Requires-Dist: fild-cfg>=0.0.1
Requires-Dist: fild-compare>=0.0.3
Requires-Dist: Pillow>=10.0.1
Requires-Dist: pytest
Requires-Dist: selenium>=4.13.0
Requires-Dist: waiting
Dynamic: license-file
